ccxtpro/__init__.py
ccxtpro-1.0.1.dist-info/LICENSE.txt
ccxtpro-1.0.1.dist-info/METADATA
ccxtpro-1.0.1.dist-info/WHEEL
ccxtpro-1.0.1.dist-info/top_level.txt
ccxtpro-1.0.1.dist-info/RECORD
